{
  "info": {
    "name": "ML Sales Forecasting API",
    "description": "API for UK property price prediction using Random Forest",
    "schema": "https://schema.getpostman.com/json/collection/v2.1.0/collection.json",
    "version": "1.0.0"
  },
  "variable": [
    {
      "key": "base_url",
      "value": "http://localhost:8000",
      "type": "string"
    }
  ],
  "item": [
    {
      "name": "Root",
      "item": [
        {
          "name": "API Information",
          "request": {
            "method": "GET",
            "header": [],
            "url": {
              "raw": "{{base_url}}/",
              "host": ["{{base_url}}"],
              "path": [""]
            },
            "description": "Get basic API information and available endpoints"
          }
        }
      ]
    },
    {
      "name": "Health",
      "item": [
        {
          "name": "Health Check",
          "request": {
            "method": "GET",
            "header": [],
            "url": {
              "raw": "{{base_url}}/api/v1/health",
              "host": ["{{base_url}}"],
              "path": ["api", "v1", "health"]
            },
            "description": "Check if service is running and model is loaded"
          }
        },
        {
          "name": "Model Information",
          "request": {
            "method": "GET",
            "header": [],
            "url": {
              "raw": "{{base_url}}/api/v1/model/info",
              "host": ["{{base_url}}"],
              "path": ["api", "v1", "model", "info"]
            },
            "description": "Get detailed metadata about the ML model"
          }
        }
      ]
    },
    {
      "name": "Predictions",
      "item": [
        {
          "name": "Predict - Terraced in London",
          "request": {
            "method": "POST",
            "header": [
              {
                "key": "Content-Type",
                "value": "application/json"
              }
            ],
            "body": {
              "mode": "raw",
              "raw": "{\n  \"property_type\": \"T\",\n  \"old_new\": \"N\",\n  \"duration\": \"F\",\n  \"county\": \"GREATER LONDON\",\n  \"postcode\": \"SW1A 1AA\",\n  \"year\": 2024\n}"
            },
            "url": {
              "raw": "{{base_url}}/api/v1/predict",
              "host": ["{{base_url}}"],
              "path": ["api", "v1", "predict"]
            },
            "description": "Predict price for a terraced house in Greater London (expected ~£350k)"
          }
        },
        {
          "name": "Predict - Detached in Surrey",
          "request": {
            "method": "POST",
            "header": [
              {
                "key": "Content-Type",
                "value": "application/json"
              }
            ],
            "body": {
              "mode": "raw",
              "raw": "{\n  \"property_type\": \"D\",\n  \"old_new\": \"Y\",\n  \"duration\": \"F\",\n  \"county\": \"SURREY\",\n  \"postcode\": \"GU1 1AA\",\n  \"year\": 2024\n}"
            },
            "url": {
              "raw": "{{base_url}}/api/v1/predict",
              "host": ["{{base_url}}"],
              "path": ["api", "v1", "predict"]
            },
            "description": "Predict price for a new detached house in Surrey (expected ~£1M+)"
          }
        },
        {
          "name": "Predict - Flat in Manchester",
          "request": {
            "method": "POST",
            "header": [
              {
                "key": "Content-Type",
                "value": "application/json"
              }
            ],
            "body": {
              "mode": "raw",
              "raw": "{\n  \"property_type\": \"F\",\n  \"old_new\": \"N\",\n  \"duration\": \"L\",\n  \"county\": \"GREATER MANCHESTER\",\n  \"postcode\": \"M1 1AA\",\n  \"year\": 2024\n}"
            },
            "url": {
              "raw": "{{base_url}}/api/v1/predict",
              "host": ["{{base_url}}"],
              "path": ["api", "v1", "predict"]
            },
            "description": "Predict price for a leasehold flat in Manchester (expected ~£236k)"
          }
        }
      ]
    },
    {
      "name": "Error Examples",
      "item": [
        {
          "name": "Error - Invalid Property Type",
          "request": {
            "method": "POST",
            "header": [
              {
                "key": "Content-Type",
                "value": "application/json"
              }
            ],
            "body": {
              "mode": "raw",
              "raw": "{\n  \"property_type\": \"X\",\n  \"old_new\": \"N\",\n  \"duration\": \"F\",\n  \"county\": \"GREATER LONDON\",\n  \"postcode\": \"SW1A 1AA\",\n  \"year\": 2024\n}"
            },
            "url": {
              "raw": "{{base_url}}/api/v1/predict",
              "host": ["{{base_url}}"],
              "path": ["api", "v1", "predict"]
            },
            "description": "Test validation error - property_type must match pattern ^[DSTFO]$"
          }
        },
        {
          "name": "Error - Missing Required Fields",
          "request": {
            "method": "POST",
            "header": [
              {
                "key": "Content-Type",
                "value": "application/json"
              }
            ],
            "body": {
              "mode": "raw",
              "raw": "{\n  \"property_type\": \"T\",\n  \"old_new\": \"N\",\n  \"duration\": \"F\",\n  \"year\": 2024\n}"
            },
            "url": {
              "raw": "{{base_url}}/api/v1/predict",
              "host": ["{{base_url}}"],
              "path": ["api", "v1", "predict"]
            },
            "description": "Test validation error - county and postcode are required"
          }
        },
        {
          "name": "Error - Invalid Year",
          "request": {
            "method": "POST",
            "header": [
              {
                "key": "Content-Type",
                "value": "application/json"
              }
            ],
            "body": {
              "mode": "raw",
              "raw": "{\n  \"property_type\": \"T\",\n  \"old_new\": \"N\",\n  \"duration\": \"F\",\n  \"county\": \"GREATER LONDON\",\n  \"postcode\": \"SW1A 1AA\",\n  \"year\": 1990\n}"
            },
            "url": {
              "raw": "{{base_url}}/api/v1/predict",
              "host": ["{{base_url}}"],
              "path": ["api", "v1", "predict"]
            },
            "description": "Test validation error - year must be >= 1995"
          }
        }
      ]
    }
  ]
}

